{
	"cemu": {
		"name": "Cemu",
		"sys": "wiiu",
		"site": "http://cemu.info/",
		"patreon": "https://www.patreon.com/cemu",
		"discord": "https://discord.gg/5psYsup",
		"appRegex": {
			"linux": "Cemu\\.exe",
			"mac": "Cemu\\.exe",
			"win": "Cemu\\.exe"
		},
		"cmd": {
			"linux": ["wine", "${app}", "-g", "${game}", "-f"],
			"mac": ["wine", "${app}", "-g", "${game}", "-f"],
			"win": ["${app}", "-g", "${game}", "-f"]
		},
		"install": {
			"linux-x64": {
				"portable": "https://github.com/cemu-project/Cemu/releases/download/v2.0-18/Cemu-2.0-18-x86_64.AppImage"
			},
			"mac-arm64": {
				"installer": "https://github.com/cemu-project/Cemu/releases/download/v2.0-18/cemu-2.0-18-macos-12-x64.dmg"
			},
			"mac-x64": {
				"installer": "https://github.com/cemu-project/Cemu/releases/download/v2.0-18/cemu-2.0-18-macos-12-x64.dmg"
			},
			"win-x64": {
				"portable": "https://github.com/cemu-project/Cemu/releases/download/v2.0-18/cemu-2.0-18-windows-x64.zip"
			}
		}
	}
}
