{"9":[],"a":[{"title":"Action Replay DS","url":"2890"},{"title":"Advance Wars Dual Strike","url":"680"},{"title":"Advance Wars: Days of Ruin","url":"5747"},{"title":"Age of Empires: The Age of Kings","url":"1185"},{"title":"Aliens Infestation","url":"9514"},{"title":"America's Test Kitchen: Let's Get Cooking","url":"7521"},{"title":"Animal Crossing: Wild World","url":"14802"},{"title":"Arkanoid DS","url":"6712"},{"title":"Art Academy","url":"14533"},{"title":"Asphalt Urban GT","url":"526"},{"title":"Asphalt Urban GT 2","url":"2604"},{"title":"Assassin's Creed II: Discovery","url":"8669"},{"title":"Avalon Code","url":"7255"},{"title":"Avatar: The Last Airbender","url":"14251"},{"title":"Avatar: The Last Airbender - The Burning Earth","url":"14069"},{"title":"Away: Shuffle Dungeon","url":"14260"}],"b":[{"title":"Bangai O Spirits","url":"6575"},{"title":"Battles: Prince of Persia","url":"1699"},{"title":"Big Bang Mini","url":"6776"},{"title":"Big Brain Academy","url":"3841"},{"title":"Big League Sports: Summer","url":"14534"},{"title":"Bomberman Land Touch!","url":"7186"},{"title":"Bomberman Land Touch! 2","url":"5749"},{"title":"Brain Age","url":"1172"},{"title":"Brain Age 2","url":"3965"},{"title":"Brothers in Arms DS","url":"11253"},{"title":"Burnout Legends","url":"2605"},{"title":"Bust A Move DS","url":"765"}],"c":[{"title":"Call of Duty 4: Modern Warfare","url":"11254"},{"title":"Call of Duty: Black Ops","url":"9511"},{"title":"Castlevania: Dawn of Sorrow","url":"767"},{"title":"Castlevania: Order of Ecclesia","url":"7778"},{"title":"Castlevania: Portrait of Ruin","url":"2601"},{"title":"Chibi Robo: Park Patrol","url":"3979"},{"title":"Children of Mana","url":"1307"},{"title":"Chrono Trigger","url":"7551"},{"title":"Clubhouse Games","url":"2593"},{"title":"Commando: Steel Disaster","url":"7779"},{"title":"Contact","url":"9655"},{"title":"Contra 4","url":"7193"},{"title":"Cooking Mama","url":"2603"},{"title":"Crafting Mama","url":"9962"},{"title":"Crash Boom Bang!","url":"1215"}],"d":[{"title":"Dancing With the Stars: We Dance!","url":"14535"},{"title":"Dark Spire, The","url":"9230"},{"title":"Deal or No Deal","url":"14536"},{"title":"Death Jr. and the Science Fair of Doom","url":"9660"},{"title":"Dementium: The Ward","url":"4223"},{"title":"Diddy Kong Racing","url":"7187"},{"title":"Dig Dug - Digging Strike","url":"7188"},{"title":"Diner Dash","url":"6083"},{"title":"DK Jungle Climber","url":"3894"},{"title":"Docomadake","url":"7256"},{"title":"Dragon Ball Z: Attack of the Saiyans","url":"10899"},{"title":"Dragon Quest Heroes: Rocket Slime","url":"9654"},{"title":"Dragon Quest IV: Chapters of the Chosen","url":"7639"},{"title":"Dragon Quest IX: Sentinels of the Starry Skies","url":"8711"},{"title":"Dragon Quest V: Hand of the Heavenly Bride","url":"7640"},{"title":"Dragon Quest VI: Realms of Revelation","url":"9659"},{"title":"DS-Xtreme","url":"1831"}],"e":[{"title":"Ecolis: Save the Forest","url":"7200"},{"title":"Electroplankton","url":"7391"},{"title":"Elements of Destruction","url":"5748"},{"title":"Elite Beat Agents","url":"2592"},{"title":"Etrian Odyssey II: Heroes of Lagaard","url":"7641"},{"title":"Etrian Odyssey III: The Drowned City","url":"8439"},{"title":"ezflash V","url":"2892"}],"f":[{"title":"Feel the Magic XY/XX","url":"715"},{"title":"Final Fantasy Fables: Chocobo Tales","url":"7781"},{"title":"Final Fantasy III","url":"1187"},{"title":"Final Fantasy IV","url":"7386"},{"title":"Final Fantasy Tactics A2: Grimoire of the Rift","url":"7782"},{"title":"Final Fantasy XII: Revenant Wings","url":"7642"},{"title":"Final Fantasy: Crystal Chronicles - Ring of Fates","url":"7780"},{"title":"Final Fantasy: The 4 Heroes of Light","url":"8754"},{"title":"Fire Emblem: Shadow Dragon","url":"6775"},{"title":"Flash Focus: Vision Training in Minutes A Day","url":"4085"},{"title":"Flipper Critters","url":"14805"},{"title":"Fossil Fighters","url":"7307"},{"title":"From the Abyss","url":"9295"}],"g":[{"title":"G6 Lite","url":"4033"},{"title":"Galactic Taz Ball","url":"14538"},{"title":"Game & Watch Collection","url":"7388"},{"title":"Game & Watch Collection 2","url":"11315"},{"title":"Gameboy Advance Movie Player","url":"1331"},{"title":"Ganbare Goemon: Toukai Douchuu Ooedo Tengurigaeshi no Maki","url":"7199"},{"title":"Garfield Gets Real","url":"9515"},{"title":"Geometry Wars Galaxies","url":"5645"},{"title":"Giana Sisters DS","url":"7358"},{"title":"Godzilla Unleashed: Double Smash","url":"5646"},{"title":"Goldeneye Rogue Agent","url":"2591"},{"title":"Grand Theft Auto: Chinatown Wars","url":"8752"},{"title":"Guitar Hero On Tour","url":"6297"},{"title":"Guitar Hero On Tour Decades","url":"6992"},{"title":"Guitar Hero On Tour: Modern Hits","url":"7482"}],"h":[{"title":"Happy Feet","url":"14539"},{"title":"Hotel Dusk - Room 215","url":"2596"}],"i":[{"title":"I Spy Universe","url":"14541"},{"title":"Imagine: Fashion Designer","url":"14545"}],"j":[{"title":"James Pond 2: Codename RoboCod","url":"6084"},{"title":"Jump Superstars","url":"667"},{"title":"Jump Ultimate Stars","url":"7553"}],"k":[{"title":"Kim Possible: Kimmunicator","url":"3916"},{"title":"King Kong, Peter Jackson's: The Official Game of the Movie","url":"6929"},{"title":"Kingdom Hearts 358/2 Days","url":"11255"},{"title":"Kingdom Hearts Re:Coded","url":"11256"},{"title":"Kirby Canvas Curse","url":"977"},{"title":"Kirby Mass Attack","url":"9239"},{"title":"Kirby Super Star Ultra","url":"11257"},{"title":"Kirby: Squeak Squad","url":"7783"},{"title":"Knights in the Nightmare","url":"8125"},{"title":"Konami Classics Series Arcade Hits","url":"7190"},{"title":"Kung Fu Panda 2","url":"9517"}],"l":[{"title":"Legacy of Ys: Books I & II","url":"9234"},{"title":"Legend of Kage 2, The","url":"7784"},{"title":"Legend of Zelda: Phantom Hourglass, The","url":"3966"},{"title":"Legend of Zelda: Spirit Tracks, The","url":"7785"},{"title":"Legend of Zelda: Twilight Princess Preview Trailer, The","url":"527"},{"title":"Legendary Starfy, The","url":"7243"},{"title":"Lego Battles Ninjago","url":"9518"},{"title":"Lego Harry Potter: Years 1 to 4","url":"9235"},{"title":"Lego Indiana Jones: The Original Adventures","url":"9296"},{"title":"Lego Star Wars III: The Clone Wars","url":"9237"},{"title":"Lego Star Wars: The Complete Saga","url":"9293"},{"title":"Line Rider 2: Unbound","url":"6576"},{"title":"Little Red Riding Hood's Zombie BBQ","url":"7197"},{"title":"Logic Machines","url":"8755"},{"title":"Looney Tunes: Duck Amuck","url":"9516"},{"title":"Lost in Blue","url":"1700"},{"title":"Lost Magic","url":"14102"},{"title":"Luminous Arc","url":"9240"},{"title":"Lunar Knights","url":"7208"},{"title":"Lunar: Dragon Song","url":"9299"},{"title":"Lux Pain","url":"7260"}],"m":[{"title":"M3 DS Simply","url":"2599"},{"title":"Magical StarSign","url":"1308"},{"title":"Magnetica","url":"1173"},{"title":"Mario & Luigi: Bowser's Inside Story","url":"7305"},{"title":"Mario & Sonic at the Olympic Winter Games","url":"11258"},{"title":"Mario and Luigi: Partners in Time","url":"717"},{"title":"Mario Hoops 3 on 3","url":"1216"},{"title":"Mario Kart DS","url":"674"},{"title":"Mario Party DS","url":"5647"},{"title":"Mario Vs. Donkey Kong 2: March Of The Minis","url":"2602"},{"title":"Mario vs. Donkey Kong: Mini-Land Mayhem!","url":"9512"},{"title":"Master of Illusion","url":"5648"},{"title":"Mechanic Master","url":"6727"},{"title":"Mega Man ZX","url":"2597"},{"title":"Mega Man ZX Advent","url":"5877"},{"title":"Megaman Starforce Dragon","url":"7001"},{"title":"Megaman Starforce Leo","url":"7002"},{"title":"Megaman Starforce Pegasus","url":"7003"},{"title":"Memory Expansion Pak","url":"14286"},{"title":"Metal Slug 7","url":"9510"},{"title":"Meteos","url":"716"},{"title":"Meteos - Disney Magic","url":"7185"},{"title":"Metroid Prime Hunters","url":"1054"},{"title":"Metroid Prime Hunters: First Hunt","url":"43"},{"title":"Metroid Prime Pinball","url":"675"},{"title":"Michael Jackson: The Experience","url":"14548"},{"title":"Minute To Win It","url":"14549"},{"title":"Moero! Nekketsu Rhythm Damashii: Osu! Tatakae! Ouendan 2","url":"7194"},{"title":"Monopoly Boggle Yahtzee Battleship","url":"2606"},{"title":"MX vs. ATX Untamed","url":"5750"},{"title":"Mystery Case Files: MillionHeir","url":"6577"}],"n":[{"title":"Namco Museum DS","url":"11259"},{"title":"Nanostray","url":"1204"},{"title":"Nanostray 2","url":"5911"},{"title":"Napoleon Dynamite: The Game","url":"5751"},{"title":"Naruto: Ninja Destiny","url":"5910"},{"title":"Naruto: Path of the Ninja","url":"4224"},{"title":"Neves","url":"5649"},{"title":"New Super Mario Brothers","url":"1174"},{"title":"New Zealand Story Revolution","url":"9236"},{"title":"Nine Hours, Nine Persons, Nine Doors","url":"8668"},{"title":"Nintendo DS Download Station Volume 1","url":"3802"},{"title":"Nintendo DS Download Station Volume 2","url":"3803"},{"title":"Nintendo DS Download Station Volume 3","url":"3804"},{"title":"Nintendo DS Download Station Volume 4","url":"3805"},{"title":"Nintendo DS Download Station Volume 5","url":"3806"},{"title":"Nintendo DS Download Station Volume 6","url":"3807"},{"title":"Nintendo DS Lite Console","url":"7496"},{"title":"Nintendo Touch Golf: Birdie Challenge","url":"2607"},{"title":"Nintendogs","url":"681"},{"title":"Nostalgia","url":"8753"}],"o":[{"title":"Orcs & Elves","url":"7189"}],"p":[{"title":"Panzer Tactics DS","url":"7017"},{"title":"Passcard","url":"3801"},{"title":"Personal Trainer: Cooking","url":"6774"},{"title":"Phoenix Wright: Ace Attorney","url":"710"},{"title":"Phoenix Wright: Ace Attorney - Justice For All","url":"2595"},{"title":"Phoenix Wright: Ace Attorney - Trials And Tribulations","url":"3800"},{"title":"Picross DS","url":"14329"},{"title":"Plants vs. Zombies","url":"9513"},{"title":"Point Blank DS","url":"7198"},{"title":"Pokémon Black Version","url":"14142"},{"title":"Pokémon Black Version 2","url":"14143"},{"title":"Pokémon Conquest","url":"14141"},{"title":"Pokémon Diamond Version","url":"14144"},{"title":"Pokémon HeartGold Version","url":"14145"},{"title":"Pokémon Mystery Dungeon: Blue Rescue Team","url":"14154"},{"title":"Pokémon Pearl Version","url":"14146"},{"title":"Pokémon Platinum Version","url":"14151"},{"title":"Pokémon Ranger: Shadows of Almia","url":"14147"},{"title":"Pokémon SoulSilver Version","url":"14148"},{"title":"Pokémon White Version","url":"14149"},{"title":"Pokémon White Version 2","url":"14150"},{"title":"Polarium","url":"2608"},{"title":"Prince of Persia: The Fallen King","url":"8756"},{"title":"Professor Layton and the Curious Village","url":"5772"},{"title":"Professor Layton and the Diabolical Box","url":"8758"},{"title":"Puyo Pop Fever","url":"1052"},{"title":"Puzzle de Harvest Moon","url":"9961"},{"title":"Puzzle Quest","url":"5588"},{"title":"Puzzler Collection","url":"6713"}],"q":[],"r":[{"title":"R4 - Revolution for DS (NDS/NDSL)","url":"2902"},{"title":"Real Madrid the game","url":"11316"},{"title":"Resident Evil Deadly Silence","url":"1701"},{"title":"Retro Atari Classics","url":"7110"},{"title":"Retro Game Challenge","url":"6777"},{"title":"Retro Game Challenge 2","url":"14259"},{"title":"Rhythm 'n Notes","url":"4218"},{"title":"Rhythm Heaven","url":"9929"},{"title":"Ridge Racer DS","url":"745"},{"title":"Rumble Pak","url":"14287"}],"s":[{"title":"Scribblenauts","url":"8401"},{"title":"Scurge: Hive","url":"2636"},{"title":"Shawn Johnson Gymnastics","url":"14550"},{"title":"Shin Megami Tensei: Devil Survivor","url":"9241"},{"title":"Sid Meier's Civilization Revolution","url":"7018"},{"title":"SimCity: Creator","url":"8757"},{"title":"Simpsons Game, The","url":"9298"},{"title":"Sims 2, The: Castaway","url":"6989"},{"title":"Snowboard Kids","url":"1053"},{"title":"Sonic and Sega All-Stars Racing","url":"9294"},{"title":"Sonic Chronicles: The Dark Brotherhood","url":"9508"},{"title":"Sonic Classic Collection","url":"9229"},{"title":"Sonic Colors","url":"9507"},{"title":"Sonic Rush","url":"747"},{"title":"Sonic Rush Adventure","url":"9509"},{"title":"Space Invaders Extreme","url":"6714"},{"title":"Space Invaders Revolution","url":"2610"},{"title":"Spectrobes","url":"7670"},{"title":"Spiderman Web of Shadows","url":"6862"},{"title":"Splitner Cell Chaos Theory","url":"1802"},{"title":"Sprung","url":"711"},{"title":"Star Trek - Tactical Assault","url":"7016"},{"title":"Star Wars Episode III: Revenge Of The Sith","url":"6355"},{"title":"Starfox Command","url":"10779"},{"title":"Style Lab: Jewelry Design","url":"14551"},{"title":"Suikoden Tierkreis","url":"9297"},{"title":"Super Card","url":"2600"},{"title":"Super Dodgeball Brawlers","url":"7192"},{"title":"Super Mario 64 DS","url":"491"},{"title":"Super Princess Peach","url":"798"}],"t":[{"title":"Tecmo Superbowl Kickoff","url":"8092"},{"title":"Tetris DS","url":"821"},{"title":"Tiger Woods PGA Tour","url":"2609"},{"title":"Tingle's Balloon Fight","url":"7387"},{"title":"Tony Hawk's American Sk8land","url":"751"},{"title":"Top Trumps : Doctor Who","url":"7130"},{"title":"Touch the Dead","url":"7111"},{"title":"Touchmaster","url":"6715"},{"title":"Trace Memory","url":"673"},{"title":"Transformers Autobots","url":"3752"},{"title":"Transformers Decepticons","url":"3753"},{"title":"Trauma Center","url":"712"},{"title":"Tropix!","url":"14552"}],"u":[{"title":"Ultimate Mortal Kombat","url":"5651"},{"title":"Urbz: Sims in the City, The","url":"1051"}],"v":[{"title":"Viewtiful Joe: Double Trouble","url":"746"},{"title":"Viva Pinata: Pocket Paradise","url":"6578"}],"w":[{"title":"Wall-E","url":"6579"},{"title":"Wario Ware Touched","url":"713"},{"title":"Wario: Master of Disguise","url":"14104"},{"title":"WarioWare D.I.Y.","url":"7518"},{"title":"Wipeout 2, abc","url":"9519"},{"title":"World Ends With You, The","url":"7000"},{"title":"WWE SmackDown vs. Raw 2008","url":"5650"}],"x":[{"title":"X-Men III","url":"1803"}],"y":[{"title":"Yoshi Touch & Go","url":"492"},{"title":"Yoshi's Island DS","url":"2594"}],"z":[{"title":"Zhu Zhu Puppies","url":"14553"},{"title":"Zoo Keeper","url":"766"}]}